saleae_enrichable_analyzer/__init__.py
saleae_enrichable_analyzer/base.py
saleae_enrichable_analyzer/scripts/__init__.py
saleae_enrichable_analyzer/scripts/i2c/AD799x.py
saleae_enrichable_analyzer/scripts/i2c/INA219.py
saleae_enrichable_analyzer/scripts/i2c/__init__.py
saleae_enrichable_analyzer/scripts/i2c/base.py
saleae_enrichable_analyzer/scripts/spi/SC16IS7xx.py
saleae_enrichable_analyzer/scripts/spi/__init__.py
saleae_enrichable_analyzer/scripts/spi/base.py
saleae_enrichable_analyzer-1.2.0.dist-info/METADATA
saleae_enrichable_analyzer-1.2.0.dist-info/WHEEL
saleae_enrichable_analyzer-1.2.0.dist-info/top_level.txt
saleae_enrichable_analyzer-1.2.0.dist-info/RECORD
