Metadata-Version: 2.1
Name: saleae-enrichable-analyzer
Version: 1.2.0
Summary: Easily generate custom markers and bubble text for arbitrary protocols
Home-page: https://github.com/coddingtonbear/python-saleae-enrichable-analyzer
Author: Adam Coddington
Author-email: me@adamcoddington.net
License: UNKNOWN
Platform: UNKNOWN
Classifier: Development Status :: 4 - Beta
Classifier: License :: OSI Approved :: MIT License
Classifier: Programming Language :: Python :: 3
